tsdeque/__init__.py
tsdeque/core.py
tsdeque/devent.py
tsdeque/exceptions.py
tsdeque/logger.py
tsdeque/timer.py
tsdeque/counter/__init__.py
tsdeque/counter/core.py
tsdeque/counter/exceptions.py
tsdeque/counter/nulldevent.py
tsdeque/counter/threshold.py
tsdeque-1.0.1.dist-info/licenses/LICENSE
tsdeque-1.0.1.dist-info/METADATA
tsdeque-1.0.1.dist-info/WHEEL
tsdeque-1.0.1.dist-info/top_level.txt
tsdeque-1.0.1.dist-info/RECORD
