Metadata-Version: 2.4
Name: tsdeque
Version: 1.0.1
Summary: Thread-safe double-ended queue
Author-email: kotmarkot <andrey.patrusov@gmail.com>
License: MIT
Project-URL: Homepage, https://github.com/PATRUSOV/python-thread-safe-deque
Keywords: deque,thread-safe,concurrency,multithreading,queue
Classifier: Programming Language :: Python :: 3
Classifier: Programming Language :: Python :: 3.10
Classifier: Programming Language :: Python :: 3.11
Classifier: Programming Language :: Python :: 3.12
Classifier: License :: OSI Approved :: MIT License
Classifier: Operating System :: OS Independent
Classifier: Development Status :: 5 - Production/Stable
Classifier: Intended Audience :: Developers
Classifier: Topic :: Software Development :: Libraries
Requires-Python: >=3.10
License-File: LICENSE
Provides-Extra: dev
Requires-Dist: pytest>=7.0; extra == "dev"
Dynamic: license-file
